rsl_python_template/__init__.py
rsl_python_template-0.1.8.dist-info/WHEEL
rsl_python_template-0.1.8.dist-info/METADATA
rsl_python_template-0.1.8.dist-info/RECORD
